{
  "problem_number": 445,
  "thread_url": "https://www.erdosproblems.com/forum/thread/445",
  "retrieved_at": "2026-07-10T23:17:12.484233+00:00",
  "page_title": "445 Discussion Thread | Erdős Problems",
  "source_html_sha256": "52092f4b2a0461b4ddc5387d422396bed4da2fcb44dc7019e62fca0d88f18073",
  "comment_count": 1,
  "comments": [
    {
      "post_id": "769",
      "text": "See this MathOverflow question. Based on this, I would expect Kloosterman sum methods to handle the case $c>3/4$, but that it is open to even reach the threshold $c=3/4$. On the other hand there is a lot of scope to get some sort of \"almost all\" result here.",
      "meta": "TerenceTao — 04:43 on 29 Sep 2025 👍 0 📝 0 🤖 0"
    }
  ]
}
