{
  "catalog_fetched_at": "2026-07-12T06:30:51.455505+00:00",
  "catalog_sha256": "11097fbcc575836152a79dab9e1819ec1aa4ce665ff7d6a8f809e2110da1ba52",
  "catalog_source_url": "https://raw.githubusercontent.com/teorth/erdosproblems/main/data/problems.yaml",
  "corpus_integrity": {
    "catalog_open_records": 616,
    "local_open_latex_files": 597,
    "missing_open_problem_numbers": [
      260,
      306,
      326,
      421,
      514,
      521,
      522,
      550,
      569,
      638,
      671,
      689,
      750,
      856,
      870,
      906,
      953,
      956,
      995,
      996,
      1005,
      1039,
      1054,
      1133,
      1151
    ],
    "rankable_intersection": 591,
    "status": "degraded",
    "unexpected_problem_numbers": [
      387,
      603,
      619,
      865,
      948,
      986
    ]
  },
  "created_at": "2026-07-12T18:47:07.196375+00:00",
  "local_forum_inventory_sha256": "ed58d73e73a362c734428d4b845dc4f0a8014b404672c9cd41ff83799b05718d",
  "local_latex_inventory_sha256": "94188ff82b93120f17e0ddfd92406295283b36452968da4b8fd4097b54f162d0",
  "raw_forum_files": 597,
  "raw_latex_files": 597,
  "schema_version": 1,
  "snapshot_date": "2026-07-12",
  "snapshot_id": "20260712-c80df16efcea",
  "source_commit": "fd9c019ede4ae68ecf64df4edc2673243d1e54a8"
}
