{
  "extraction": {
    "additional_text_region": "div.problem-additional-text",
    "extractor_version": "canonical-sections-v2",
    "html_entities_decoded": true,
    "statement_region": "div#content"
  },
  "problem_number": 146,
  "raw_page": {
    "path": "raw/pages/problem_146.html",
    "sha256": "4d24223a47208805cf8bbdcbee44e298b971e0a63f2887006b81de0c27479991"
  },
  "retrieved_at": "2026-07-12T20:00:42.175415+00:00",
  "schema_version": 1,
  "sections": {
    "references": {
      "sha256": "b34ec62532b3d5359f7ab96b5118d39ed0b4ca7f2b832a29434cfa6a68a4a3a3",
      "source_region": "div.problem-additional-text",
      "text": "[AKS03] Alon, Noga and Krivelevich, Michael and Sudakov, Benny, Tur\\'{a}n numbers of bipartite graphs and related\nRamsey-type questions. Combin. Probab. Comput. (2003), 477-494.\n \n [ErSi84] Erd\\H{o}s, P. and Simonovits, M., Cube-supersaturated graphs and related problems. Progress in graph theory (Waterloo, Ont., 1982) (1984), 203-218."
    },
    "remarks": {
      "sha256": "cb07736b03c3efd56b10435f42d1b014483b8de25424382603b59ee78d781f55",
      "source_region": "div.problem-additional-text",
      "text": "Conjectured by Erd\\H{o}s and Simonovits \\cite{ErSi84}. Open even for $r=2$. Alon, Krivelevich, and Sudakov \\cite{AKS03} have proved\\[\\mathrm{ex}(n;H) \\ll n^{2-1/4r}.\\]They also prove the full Erd\\H{o}s-Simonovits conjectured bound if $H$ is bipartite and the maximum degree in one side of the bipartition is $r$. \n\nSee also [113] and [147].\n\nThis problem is #43 in Extremal Graph Theory in the graphs problem collection."
    },
    "statement": {
      "sha256": "80427312782480db1c054b1bb0680afee62e6e441ae3308dd791c3f3a5ecf0db",
      "source_region": "div#content",
      "text": "If $H$ is bipartite and is $r$-degenerate, that is, every induced subgraph of $H$ has minimum degree $\\leq r$, then\\[\\mathrm{ex}(n;H) \\ll n^{2-1/r}.\\]"
    }
  },
  "source_url": "https://www.erdosproblems.com/latex/146"
}
