{
  "extraction": {
    "additional_text_region": "div.problem-additional-text",
    "extractor_version": "canonical-sections-v2",
    "html_entities_decoded": true,
    "statement_region": "div#content"
  },
  "problem_number": 1145,
  "raw_page": {
    "path": "raw/pages/problem_1145.html",
    "sha256": "80c3968767f560ceb8e0af9d281e58e93307d7682942d96da78eebf568b326c2"
  },
  "retrieved_at": "2026-07-12T20:00:42.175415+00:00",
  "schema_version": 1,
  "sections": {
    "references": {
      "sha256": "e3b0c44298fc1c149afbf4c8996fb92427ae41e4649b934ca495991b7852b855",
      "source_region": "div.problem-additional-text",
      "text": ""
    },
    "remarks": {
      "sha256": "725fd9254fe4827ec2901c6135db0438b4d4103c3873fdeff37845fa15748a4e",
      "source_region": "div.problem-additional-text",
      "text": "A conjecture of Erd\\H{o}s and S\\'{a}rk\\\"{o}zy. Some condition relating $A$ and $B$ is necessary since, for example, if $A$ is the set of all integers with only even binary digits and $B$ is the set of all integers with only odd binary digits then $1_A\\ast 1_B(n)=1$ for all $n$.\n\nThis is a stronger form of [28]. See also [331]."
    },
    "statement": {
      "sha256": "9e09518f21eee7d75924908bc961f9ed57d7ef5059020df6754c59adc2b5d6e7",
      "source_region": "div#content",
      "text": "Let $A=\\{1\\leq a_1<a_2<\\cdots\\}$ and $B=\\{1\\leq b_1<b_2<\\cdots\\}$ be sets of integers with $a_n/b_n\\to 1$. \n\nIf $A+B$ contains all sufficiently large positive integers then is it true that $\\limsup 1_A\\ast 1_B(n)=\\infty$?"
    }
  },
  "source_url": "https://www.erdosproblems.com/latex/1145"
}
